Metadata-Version: 2.1
Name: ititer
Version: 0.1.3
Summary: Infer inflection and endpoint titers from serial dilution assays using Bayesian hierarchical modelling.
Home-page: https://github.com/IRI-UW-Bioinformatics/ititer
Download-URL: https://github.com/IRI-UW-Bioinformatics/ititer/archive/refs/tags/0.1.2.tar.gz
Author: David J. Pattinson
Author-email: david.pattinson@wisc.edu
Maintainer: David J. Pattinson
Maintainer-email: david.pattinson@wisc.edu
License: MIT
Keywords: bayesian,dose response,dose,response,virology,elisa,sigmoid
Platform: Linux
Platform: MacOS
Platform: Windows
Classifier: Development Status :: 4 - Beta
Classifier: Environment :: Console
Classifier: Programming Language :: Python
License-File: LICENSE.md
